baretypes/__init__.py
baretypes/py.typed
baretypes/types.py
baretypes-3.6.4.dist-info/LICENSE
baretypes-3.6.4.dist-info/WHEEL
baretypes-3.6.4.dist-info/METADATA
baretypes-3.6.4.dist-info/RECORD
