Metadata-Version: 2.1
Name: baretypes
Version: 3.6.4
Summary: Types for bareASGI and bareClient
Home-page: https://github.com/rob-blackbourn/bareTypes
License: Apache-2.0
Author: Rob Blackbourn
Author-email: rob.blackbourn@gmail.com
Requires-Python: >=3.7,<4.0
Classifier: License :: OSI Approved :: Apache Software License
Classifier: Programming Language :: Python :: 3
Classifier: Programming Language :: Python :: 3.7
Classifier: Programming Language :: Python :: 3.8
Classifier: Programming Language :: Python :: 3.9
Project-URL: Repository, https://github.com/rob-blackbourn/bareTypes
